preptext/__dataset.py
preptext/__datastorage.py
preptext/__entry.py
preptext/__field.py
preptext/__init__.py
preptext/__vocab.py
preptext/converter.py
preptext/dataset.py
preptext/datastorage.py
preptext/entry.py
preptext/field.py
preptext/vocab.py
preptext-0.1.21.dist-info/LICENSE
preptext-0.1.21.dist-info/METADATA
preptext-0.1.21.dist-info/WHEEL
preptext-0.1.21.dist-info/top_level.txt
preptext-0.1.21.dist-info/zip-safe
preptext-0.1.21.dist-info/RECORD
